{
  "currentVersion": "1.6.0",
  "releases": [
    {
      "version": "1.6.0",
      "date": "2026-06-21",
      "title": "新增「限登入觀看」簡報，並在登入後自動返回原簡報",
      "type": "new",
      "changes": [
        { "tag": "new", "text": "簡報新增「限登入觀看」可見性：在新增或編輯簡報時可選擇此模式，讓任何已登入的使用者都能觀看，但未登入的訪客無法存取，適合只想分享給站內成員、又不必逐一設定密碼的情境。" },
        { "tag": "improved", "text": "未登入時點開「限登入觀看」的簡報，會先被導向登入頁，登入完成後自動回到原本想看的那份簡報，不必再手動尋找連結。" },
        { "tag": "fixed", "text": "修正登入後一律跳回工作區的問題：現在登入頁會記住你原本要前往的頁面，登入後直接帶你回到該處。" }
      ]
    },
    {
      "version": "1.5.1",
      "date": "2026-06-21",
      "title": "強化容器安全性並修補相依套件已知漏洞",
      "type": "fixed",
      "changes": [
        { "tag": "fixed", "text": "修補多個相依套件的已知安全漏洞（含一項高風險項目），並精簡正式環境的容器內容、移除其中不需要且常帶漏洞的工具，讓線上服務更安全；一般使用者的操作與畫面維持不變。" },
        { "tag": "improved", "text": "自行架設者：使用官方 Docker 映像部署時無需任何調整，沿用原本的資料庫連線設定即可正常啟動並自動套用資料庫更新。" }
      ]
    },
    {
      "version": "1.5.0",
      "date": "2026-06-21",
      "title": "公開註冊開關、Google 帳號綁定與密碼保護公開簡報",
      "type": "new",
      "changes": [
        { "tag": "warning", "text": "密碼保護簡報的顯示方式調整：過去密碼保護簡報不會出現在公開列表，本次更新後它們會一併顯示在首頁公開藝廊與清單中（標示「密碼保護」），但訪客仍須輸入正確密碼才能觀看內容。若你有不希望標題被看到的簡報，請改設為「私人」或「不公開列表」。" },
        { "tag": "new", "text": "管理員可開關「公開註冊」：在使用者管理頁新增開關，關閉後訪客就無法以 Email 或首次 Google 登入自行建立帳號，改由管理員控管成員；網站第一位使用者仍可正常註冊並成為管理員。" },
        { "tag": "new", "text": "新增 Google 帳號綁定：登入後可在個人設定頁，使用與目前帳號相同且已驗證的 Google Email 綁定 Google 帳號，之後即可直接用 Google 一鍵登入；綁定連結具時效保護，避免被他人冒用。" },
        { "tag": "new", "text": "管理員可刪除使用者：使用者管理頁每位成員新增「刪除」按鈕，可永久移除帳號及其建立的所有簡報；系統會阻擋刪除自己的帳號或最後一位有效管理員，避免誤刪後無人可管理。" },
        { "tag": "improved", "text": "公開簡報可加設選用密碼：簡報密碼保護改為「公開簡報的選用密碼」，你可以讓簡報出現在公開列表、同時要求訪客先輸入密碼才能觀看；在編輯設定頁可隨時新增、更換或移除密碼。" },
        { "tag": "improved", "text": "自行架設者：本次更新新增一張設定資料表，會在啟動時自動套用，沿用原本的資料庫連線設定即可；執行環境也升級至新版 Node，使用官方 Docker 映像者無需額外調整。建議升級前先備份資料庫。" }
      ]
    },
    {
      "version": "1.4.0",
      "date": "2026-06-21",
      "title": "升級底層框架與套件，強化安全與穩定性",
      "type": "improved",
      "changes": [
        { "tag": "improved", "text": "全面升級網站的底層框架、資料庫工具與多個函式庫至最新版本，並修補多個已知安全漏洞（含先前評為重大與高風險的項目），整體運作更安全、更穩定；一般使用者的操作與畫面維持不變。" },
        { "tag": "improved", "text": "自行架設者：使用官方 Docker 映像部署時無需額外調整，沿用原本的資料庫連線設定即可正常啟動並自動套用資料庫更新。" }
      ]
    },
    {
      "version": "1.3.1",
      "date": "2026-06-21",
      "title": "首頁改為公開簡報藝廊，一進站就看得到",
      "type": "improved",
      "changes": [
        { "tag": "improved", "text": "首頁改版：一打開網站首頁，就直接看到所有公開分享的簡報，不必再多點一次「探索」。沿用原有的關鍵字搜尋與最新／最熱門排序，未登入也能直接瀏覽。原本的「探索」頁面網址仍可使用，會自動帶你回到首頁，舊連結不會失效。" }
      ]
    },
    {
      "version": "1.3.0",
      "date": "2026-06-20",
      "title": "可上傳檔案直接更新既有簡報",
      "type": "new",
      "changes": [
        { "tag": "new", "text": "工作區每份簡報新增「更新」按鈕：可上傳新檔案直接覆蓋既有簡報內容，不必刪掉重建——Markdown 簡報上傳 .md 檔、PowerPoint 簡報上傳 .pptx 重新轉換。僅簡報的擁有者或管理員可更新。" }
      ]
    },
    {
      "version": "1.2.1",
      "date": "2026-06-20",
      "title": "修正簡報卡片沒有封面的問題",
      "type": "fixed",
      "changes": [
        { "tag": "fixed", "text": "修正「簡報工作區」與「探索公開簡報」中，每份簡報卡片都沒有封面、只顯示同一個圖示的問題；現在卡片會以簡報的第一張投影片作為封面預覽，更容易一眼辨識。" }
      ]
    },
    {
      "version": "1.2.0",
      "date": "2026-06-20",
      "title": "簡報精美主題版面與播放進場動畫",
      "type": "new",
      "changes": [
        { "tag": "new", "text": "簡報新增「主題版面」：在 Markdown 中套用一組安全的版面標籤，就能做出深色／淺色主題、漸層標題、數據卡、多欄排版等精美設計，不需自己寫程式或樣式。" },
        { "tag": "new", "text": "播放簡報時新增進場動畫：投影片會淡入、內容逐項浮現，讓簡報更有節奏感；若系統開啟「減少動態效果」會自動轉為靜態，照顧不適者。" },
        { "tag": "new", "text": "提供多份精美的範例簡報（產品發表、年度報告、技術提案），可直接匯入後參考或修改。" }
      ]
    },
    {
      "version": "1.1.1",
      "date": "2026-06-20",
      "title": "全站介面重新設計與無障礙改進",
      "type": "improved",
      "changes": [
        { "tag": "improved", "text": "全站介面重新設計：採用新的配色、字體與字級系統，整體更現代、專業，文字也更清晰易讀。" },
        { "tag": "improved", "text": "以鍵盤瀏覽時會顯示清楚的焦點外框，讓使用者隨時看得到目前所在位置（無障礙改進）。" },
        { "tag": "improved", "text": "尊重系統「減少動態效果」偏好設定：開啟時介面會自動降低或關閉動畫，減少不適。" },
        { "tag": "improved", "text": "投影片內的外部連結改為在新分頁開啟，並加上安全屬性，瀏覽更安心。" }
      ]
    },
    {
      "version": "1.1.0",
      "date": "2026-06-20",
      "title": "改用 Markdown 編輯、支援上傳簡報與公開藝廊",
      "type": "new",
      "changes": [
        { "tag": "warning", "text": "投影片編輯方式改為 Markdown；以舊版圖形拖拉編輯器製作的投影片在升級後可能顯示為空白，需重新以 Markdown 編輯。建議升級前先備份資料庫。" },
        { "tag": "new", "text": "投影片改用 Markdown 撰寫：左側輸入、右側即時預覽，並以單獨一行的「---」分頁，編輯更快、更專注於內容。" },
        { "tag": "new", "text": "可上傳 Markdown 檔（.md）直接匯入成一份可繼續編輯的簡報，系統會依「---」自動分頁。" },
        { "tag": "new", "text": "可上傳 PowerPoint 檔（.pptx），系統會自動轉成每頁圖片供線上唯讀瀏覽，方便分享既有簡報。" },
        { "tag": "new", "text": "新增「探索」公開簡報藝廊，可瀏覽全站所有公開簡報，並用關鍵字搜尋、依最新或最熱門排序。" },
        { "tag": "new", "text": "公開簡報開放任何人觀看：未登入的訪客也能直接瀏覽公開藝廊與公開簡報；私人與密碼保護的簡報仍需登入或輸入密碼。" },
        { "tag": "removed", "text": "移除舊版的圖形（拖拉元素）投影片編輯器，統一改用 Markdown 編輯。" }
      ]
    },
    {
      "version": "1.0.1",
      "date": "2026-06-20",
      "title": "修正正式環境登入問題並簡化部署流程",
      "type": "fixed",
      "changes": [
        { "tag": "fixed", "text": "修正將網站部署到正式環境（位於反向代理或自訂網域後）時可能無法登入的問題，部署後的網站現在可正常登入與使用。" },
        { "tag": "improved", "text": "部署時資料庫結構會在服務啟動時自動更新，不再需要手動執行更新步驟，降低部署出錯的機會。" },
        { "tag": "improved", "text": "官方 Docker 映像檔現在同時發布於 Docker Hub 與 GitHub Container Registry，方便自行架設者取得與部署。" }
      ]
    },
    {
      "version": "1.0.0",
      "date": "2026-06-20",
      "title": "SlideForge 首次發布：線上投影片建立、瀏覽與權限管理",
      "type": "new",
      "changes": [
        { "tag": "new", "text": "推出線上投影片平台：使用者可在網頁上逐頁瀏覽簡報，用左右鍵或畫面按鈕切換頁面，並支援全螢幕播放。" },
        { "tag": "new", "text": "提供管理員、使用者、訪客三種身分。第一位註冊的帳號自動成為管理員，之後註冊者預設為訪客，需由管理員指派升級。" },
        { "tag": "new", "text": "管理員可在後台調整任何帳號的身分與啟用狀態，並保留至少一名管理員以避免系統失去管理權。" },
        { "tag": "new", "text": "管理員與使用者可直接在網頁上建立、編輯投影片，加入文字、圖片與基本形狀並拖曳排版；訪客僅能瀏覽，無法編輯。" },
        { "tag": "new", "text": "每份簡報可設定獨立的瀏覽密碼，並可選擇私人、需密碼、公開或不公開列出等不同的開放範圍。" },
        { "tag": "new", "text": "系統會記錄誰在什麼時間、從哪個 IP 位址瀏覽了哪份簡報的第幾頁；管理員可查看全站記錄，使用者可查看自己簡報的瀏覽情形。" },
        { "tag": "new", "text": "支援以 Email 加密碼註冊登入，亦可使用 Google 帳號登入；密碼一律加密保存，登入與密碼驗證皆有防暴力嘗試的保護。" },
        { "tag": "new", "text": "全站採用現代化響應式介面，支援深色模式，並內建多項資安防護（輸入驗證、內容消毒、傳輸加密）以保護瀏覽與編輯安全。" }
      ]
    }
  ]
}
